{"name":"Verify the scenario when blank \u0027Password\u0027 field","id":"validation-on-sign-up-page-negative-test-case;verify-the-scenario-when-blank--password--field","testSteps":[{"number":1,"description":"When Enter \u0027Password\u0027 as blank","duration":4101,"startTime":"2021-08-25T09:28:13.539460+05:30[Asia/Calcutta]","result":"SUCCESS","precondition":false,"level":0},{"number":2,"description":"Then Verify the validation message","duration":1425,"startTime":"2021-08-25T09:28:17.640694100+05:30[Asia/Calcutta]","result":"SUCCESS","precondition":false,"level":0}],"userStory":{"id":"validation-on-sign-up-page-negative-test-case","storyName":"Validation on Sign Up Page negative test case","path":"02_Signup_negative_scenario.feature","type":"feature"},"featureTag":{"name":"Validation on Sign Up Page negative test case","type":"feature","displayName":"Validation on Sign Up Page negative test case"},"title":"Verify the scenario when blank \u0027Password\u0027 field","description":"","tags":[{"name":"Validation on Sign Up Page negative test case","type":"feature","displayName":"Validation on Sign Up Page negative test case"}],"startTime":"2021-08-25T09:28:13.531741800+05:30[Asia/Calcutta]","duration":5536,"projectKey":"","isManualTestingUpToDate":false,"manual":false,"testSource":"Cucumber","result":"SUCCESS"}