{"name":"Validate the Redeem points  in the Award points dashboard.","id":"user-must-click-on-the-award-point-and-navigated-to-the-reddemed-award-points-page;validate-the-redeem-points--in-the-award-points-dashboard.","testSteps":[{"number":1,"description":"Given User is on redeem points page","duration":150,"startTime":"2021-08-26T17:26:07.070027200+05:30[Asia/Calcutta]","result":"SUCCESS","precondition":false,"level":0},{"number":2,"description":"When Enter giftcard and amount to redeem","duration":2,"startTime":"2021-08-26T17:26:07.221820100+05:30[Asia/Calcutta]","result":"SUCCESS","precondition":false,"level":0},{"number":3,"description":"Then Validate user is able to redeem points","duration":1,"startTime":"2021-08-26T17:26:07.224811500+05:30[Asia/Calcutta]","result":"SUCCESS","precondition":false,"level":0}],"userStory":{"id":"user-must-click-on-the-award-point-and-navigated-to-the-reddemed-award-points-page","storyName":"User must click on the Award Point and navigated to the Reddemed award points page","path":"09_Award_points_positive_scenario.feature","type":"feature"},"featureTag":{"name":"User must click on the Award Point and navigated to the Reddemed award points page","type":"feature","displayName":"User must click on the Award Point and navigated to the Reddemed award points page"},"title":"Validate the Redeem points  in the Award points dashboard.","description":"","tags":[{"name":"User must click on the Award Point and navigated to the Reddemed award points page","type":"feature","displayName":"User must click on the Award Point and navigated to the Reddemed award points page"}],"startTime":"2021-08-26T17:26:07.065040200+05:30[Asia/Calcutta]","duration":161,"projectKey":"","isManualTestingUpToDate":false,"manual":false,"testSource":"Cucumber","result":"SUCCESS"}